OACrawler/__init__.py
OACrawler/core.py
OACrawler/common/__init__.py
OACrawler/common/const.py
OACrawler/common/exception.py
OACrawler/common/headers.py
OACrawler/crawler/__init__.py
OACrawler/crawler/base_crawler.py
OACrawler/crawler/codeforce_crawler.py
OACrawler/model/__init__.py
OACrawler/model/base_model.py
OACrawler/model/codeforce_model.py
OACrawler/setting/__init__.py
OACrawler/setting/base_setting.py
OACrawler/setting/codeforce_settting.py
OACrawler-1.8.0.dist-info/LICENSE
OACrawler-1.8.0.dist-info/METADATA
OACrawler-1.8.0.dist-info/WHEEL
OACrawler-1.8.0.dist-info/top_level.txt
OACrawler-1.8.0.dist-info/RECORD
